CHANGES.rst
INSTALL.rst
MANIFEST.in
README.rst
compile_pyx.sh
gpl-3.0.txt
requirements.txt
setup.py
docs/Makefile
docs/source/conf.py
docs/source/images/alg1.png
docs/source/images/alg2.png
docs/source/images/power.pdf
docs/source/images/power.png
docs/source/images/relationships.eps
docs/source/images/relationships.png
examples/c_conv_example.c
examples/c_example.c
examples/cpp_example.cpp
examples/cpp_example2.cpp
examples/matlab_example.m
examples/power.py
examples/python_conv_example.py
examples/python_example.py
examples/python_example2.py
examples/relationships.py
libmine/cppmine.cpp
libmine/cppmine.h
libmine/mine.c
libmine/mine.h
matlab/mine.m
matlab/mine_mex.c
minepy/__init__.py
minepy/mine.c
minepy/mine.pyx
minepy.egg-info/PKG-INFO
minepy.egg-info/SOURCES.txt
minepy.egg-info/dependency_links.txt
minepy.egg-info/requires.txt
minepy.egg-info/top_level.txt
minepy/scripts/mine
tests/minepy_test.py