Metadata-Version: 1.1
Name: minepy
Version: 1.2.0
Summary: minepy - Maximal Information-based Nonparametric Exploration
Home-page: http://minepy.readthedocs.io
Author: Davide Albanese
Author-email: davide.albanese@gmail.com
License: GPLv3
Download-URL: http://minepy.readthedocs.io
Platform: UNKNOWN
Classifier: Development Status :: 5 - Production/Stable
Classifier: Intended Audience :: Science/Research
Classifier: License :: OSI Approved :: GNU General Public License (GPL)
Classifier: Programming Language :: C
Classifier: Programming Language :: C++
Classifier: Programming Language :: Cython
Classifier: Programming Language :: Python
Classifier: Programming Language :: Python :: 2
Classifier: Programming Language :: Python :: 3
Classifier: Programming Language :: Other
Classifier: Operating System :: OS Independent
